[{"id":1,"name":"Green Smoothie Mix","img":"ami/1","price":250,"hook":"3.0mm","yarn":"acrylic","technique":"single","desc":"一款以日曬番茄和松子製成的濃郁青醬。"},
{"id":2,"name":"Oven-Baked Potato Chips","img":"ami/2","price":280,"hook":"3.0mm","yarn":"acrylic","technique":"single","desc":"適合發揮想像力的互動式廚房玩具組。"},
{"id":3,"name":"Cat Scratching Post with Toys","img":"ami/3","price":450,"hook":"3.0mm","yarn":"acrylic","technique":"single","desc":"輕便耐用的吊床，讓您在大自然中放鬆身心。"},
{"id":4,"name":"Whisk Set","img":"ami/4","price":120,"hook":"4.0mm","yarn":"wool","technique":"magic","desc":"便攜式營火坑，適合後院聚會。"},
{"id":5,"name":"Homestyle Beef Stew","img":"ami/5","price":70,"hook":"4.0mm","yarn":"wool","technique":"magic","desc":"搭配泰式辣醬的即食麵，方便快速用餐。"},
{"id":6,"name":"Sweet and Sour Sauce","img":"ami/6","price":30,"hook":"4.0mm","yarn":"wool","technique":"magic","desc":"採用全穀物與蜂蜜製成的經典麥片。"},
{"id":7,"name":"Workstation Laptop Stand","img":"ami/7","price":50,"hook":"4.0mm","yarn":"wool","technique":"magic","desc":"專為狗狗設計的耐用柔軟飛盤。"},
{"id":8,"name":"Couscous","img":"ami/8","price":30,"hook":"4.0mm","yarn":"acrylic","technique":"magic","desc":"酸甜果醬，塗抹於吐司或用於甜點皆宜。"},
{"id":9,"name":"Snap-On Tupperware Set","img":"ami/9","price":350,"hook":"4.0mm","yarn":"acrylic","technique":"magic","desc":"低卡路里米糕，適合當作點心。"},
{"id":10,"name":"Elderberry Syrup Kit","img":"ami/10","price":220,"hook":"4.0mm","yarn":"wool","technique":"magic","desc":"以韭蔥和馬鈴薯烹製的鹹味湯品。"}]